{
    "delivery_date": "2025-12-04",
    "buyer_name": "sun11店铺",
    "supplier_name": "益鑫",
    "delivery_order_number": "XFS2512040008",
    "style_candidates": [
        {
            "text": "H0699T-B",
            "is_red": false,
            "position": "备注栏"
        }
    ],
    "items": [
        {
            "qty": 87.7,
            "price": 46,
            "unit": "公斤",
            "raw_style_text": "8913",
            "product_description": "8913精品棉羊绒-45#米白"
        }
    ],
    "used_api_key": "sk-Rr9CXIyBuc4sq9mpEyaN8l3WhVYB8P1TpahojO1HT1bozO4B",
    "purchaser": "陈李莉",
    "final_selected_style": "H0699T-B",
    "retry_count": 1
}